tweepy_authlib/CookieSessionUserHandler.py
tweepy_authlib/XPFFHeaderGenerator.py
tweepy_authlib/__about__.py
tweepy_authlib/__init__.py
tweepy_authlib-1.7.3.dist-info/METADATA
tweepy_authlib-1.7.3.dist-info/WHEEL
tweepy_authlib-1.7.3.dist-info/RECORD
