Metadata-Version: 2.4
Name: tweepy-authlib
Version: 1.7.3
Summary: Twitter Web App (Web 版公式クライアント) の内部 API を使い、Tweepy でスクリーンネームとパスワードで認証するためのライブラリ
Project-URL: Documentation, https://github.com/tsukumijima/tweepy-authlib
Project-URL: Issues, https://github.com/tsukumijima/tweepy-authlib/issues
Project-URL: Source, https://github.com/tsukumijima/tweepy-authlib
Author: tsukumi
License: MIT License
Keywords: Library,Tweepy,Twitter
Classifier: Development Status :: 4 - Beta
Classifier: Intended Audience :: Developers
Classifier: Intended Audience :: Information Technology
Classifier: License :: OSI Approved :: MIT License
Classifier: Natural Language :: Japanese
Classifier: Programming Language :: Python
Classifier: Programming Language :: Python :: 3.9
Classifier: Programming Language :: Python :: 3.10
Classifier: Programming Language :: Python :: 3.11
Classifier: Programming Language :: Python :: 3.12
Classifier: Programming Language :: Python :: 3.13
Classifier: Programming Language :: Python :: Implementation :: CPython
Requires-Python: >=3.9
Requires-Dist: beautifulsoup4>=4.13.1
Requires-Dist: curl-cffi>=0.13.0
Requires-Dist: js2py-3-13>=0.74.1
Requires-Dist: pycryptodomex>=3.20.0
Requires-Dist: tweepy>=4.12.1
Requires-Dist: xclienttransaction>=1.0.0
